pyclustree/__init__.py
pyclustree/_clustree.py
pyclustree/_utils.py
pyclustree-0.4.1.dist-info/licenses/LICENSE
pyclustree-0.4.1.dist-info/WHEEL
pyclustree-0.4.1.dist-info/METADATA
pyclustree-0.4.1.dist-info/RECORD
