Metadata-Version: 2.4
Name: pyclustree
Version: 0.4.1
Summary: Visualize cluster assignments at different resolutions
Author: Malte Hellmig, Malte Kuehl
Maintainer-email: Malte Hellmig <m.hellmig@uke.de>, Malte Kuehl <malte.kuehl@clin.au.dk>
Requires-Python: >=3.10
Classifier: Development Status :: 3 - Alpha
Classifier: Intended Audience :: Healthcare Industry
Classifier: Intended Audience :: Science/Research
Classifier: License :: OSI Approved :: GNU General Public License v3 (GPLv3)
Classifier: Natural Language :: English
Classifier: Operating System :: OS Independent
Classifier: Programming Language :: Python :: 3 :: Only
Classifier: Programming Language :: Python :: 3.10
Classifier: Programming Language :: Python :: 3.11
Classifier: Programming Language :: Python :: 3.12
Classifier: Typing :: Typed
License-File: LICENSE
Requires-Dist: anndata
Requires-Dist: matplotlib
Requires-Dist: networkx
Requires-Dist: numpy
Requires-Dist: pandas
Requires-Dist: seaborn
Requires-Dist: session-info
Requires-Dist: coverage ; extra == "dev"
Requires-Dist: docutils>=0.8,!=0.18.*,!=0.19.* ; extra == "dev"
Requires-Dist: flit ; extra == "dev"
Requires-Dist: furo ; extra == "dev"
Requires-Dist: ipykernel ; extra == "dev"
Requires-Dist: ipython ; extra == "dev"
Requires-Dist: ipywidgets ; extra == "dev"
Requires-Dist: myst-parser ; extra == "dev"
Requires-Dist: nbsphinx ; extra == "dev"
Requires-Dist: pandas ; extra == "dev"
Requires-Dist: pandas-stubs ; extra == "dev"
Requires-Dist: pandoc ; extra == "dev"
Requires-Dist: pre-commit ; extra == "dev"
Requires-Dist: pytest ; extra == "dev"
Requires-Dist: python-igraph ; extra == "dev"
Requires-Dist: scanpy ; extra == "dev"
Requires-Dist: setuptools ; extra == "dev"
Requires-Dist: sphinx>=4 ; extra == "dev"
Requires-Dist: sphinx-autoapi ; extra == "dev"
Requires-Dist: sphinx-autodoc-typehints ; extra == "dev"
Requires-Dist: sphinx-book-theme>=1 ; extra == "dev"
Requires-Dist: sphinx-copybutton ; extra == "dev"
Requires-Dist: sphinx-design ; extra == "dev"
Requires-Dist: sphinx-rtd-theme ; extra == "dev"
Requires-Dist: sphinx-tabs ; extra == "dev"
Requires-Dist: sphinxcontrib-bibtex>=1 ; extra == "dev"
Requires-Dist: sphinxext-opengraph ; extra == "dev"
Requires-Dist: twine>=4.0.2 ; extra == "dev"
Requires-Dist: types-networkx ; extra == "dev"
Requires-Dist: scikit-learn ; extra == "sklearn"
Project-URL: Documentation, https://pyclustree.readthedocs.io/
Project-URL: Homepage, https://github.com/complextissue/pyclustree
Project-URL: Source, https://github.com/complextissue/pyclustree
Provides-Extra: dev
Provides-Extra: sklearn
